Metadata-Version: 1.1
Name: rdbtools
Version: 0.1.10
Summary: Utilities to convert Redis RDB files to JSON or SQL formats
Home-page: https://github.com/sripathikrishnan/redis-rdb-tools
Author: Sripathi Krishnan, Redis Labs
Author-email: oss@redislabs.com
License: MIT
Download-URL: https://github.com/sripathikrishnan/redis-rdb-tools/archive/rdbtools-0.1.10.tar.gz
Keywords: Redis,RDB,Export,Dump,Memory Profiler
Platform: UNKNOWN
Classifier: Development Status :: 5 - Production/Stable
Classifier: Environment :: Console
Classifier: Intended Audience :: Developers
Classifier: License :: OSI Approved :: MIT License
Classifier: Operating System :: OS Independent
Classifier: Programming Language :: Python
